{"cameraMode":{"drawMode":0,"name":"Shaded","section":"Shading Mode"},"sceneLighting":false,"audioPlay":false,"sceneViewState":{"m_AlwaysRefresh":false,"showFog":false,"showSkybox":false,"showFlares":false,"showImageEffects":false,"showParticleSystems":false,"showVisualEffectGraphs":true,"m_FxEnabled":true},"in2DMode":false,"pivot":{"x":0.6008331179618836,"y":0.8752759099006653,"z":-17.799463272094728},"rotation":{"x":0.0001913959567900747,"y":-0.9998599290847778,"z":-0.011689020320773125,"w":-0.014391015283763409},"size":10.0,"orthographic":false}